LDB_Django_Common-0.0.18-py3.8-nspkg.pth
ldb/django/conf/__init__.py
ldb/django/conf/urls.py
ldb/django/contrib/__init__.py
ldb/django/contrib/auth/__init__.py
ldb/django/contrib/auth/mixins.py
ldb/django/contrib/auth/models.py
ldb/django/contrib/auth/permissions.py
ldb/django/contrib/auth/test.py
ldb/django/contrib/auth/views.py
ldb/django/contrib/migration/__init__.py
ldb/django/db/__init__.py
ldb/django/db/migrations/__init__.py
ldb/django/db/migrations/makemigrations.py
ldb/django/forms/__init__.py
ldb/django/forms/json.py
ldb/django/forms/static/ldb/forms/forms.js
ldb/django/forms/templatetags/__init__.py
ldb/django/forms/templatetags/form_json.py
ldb/django/test/__init__.py
ldb/django/test/runner.py
ldb/django/test/testcases.py
ldb/django/view/__init__.py
ldb/django/view/generic/edit.py
LDB_Django_Common-0.0.18.dist-info/LICENSE
LDB_Django_Common-0.0.18.dist-info/METADATA
LDB_Django_Common-0.0.18.dist-info/WHEEL
LDB_Django_Common-0.0.18.dist-info/entry_points.txt
LDB_Django_Common-0.0.18.dist-info/namespace_packages.txt
LDB_Django_Common-0.0.18.dist-info/top_level.txt
LDB_Django_Common-0.0.18.dist-info/RECORD
